bayan/__init__.py
bayan/cleaner.py
bayan/exporter.py
bayan/extractor.py
bayan/llm_client.py
bayan/parser.py
bayan/tables.py
bayan/utils.py
bayan_lib-0.1.0.dist-info/licenses/LICENSE
tests/__init__.py
tests/test_basic.py
bayan_lib-0.1.0.dist-info/METADATA
bayan_lib-0.1.0.dist-info/WHEEL
bayan_lib-0.1.0.dist-info/top_level.txt
bayan_lib-0.1.0.dist-info/RECORD
