Metadata-Version: 2.4
Name: bayan-lib
Version: 0.1.0
Summary: Extract structured, meaningful information from academic PDFs
Home-page: https://github.com/atomicKhalil/bayan
Author: Khalil Selmi
Author-email: Khalil Selmi <khalil.selmi.dev@gmail.com>
License: MIT
Project-URL: Homepage, https://github.com/atomicKhalil/bayan
Project-URL: Documentation, https://github.com/atomicKhalil/bayan#readme
Project-URL: Repository, https://github.com/atomicKhalil/bayan
Project-URL: Issues, https://github.com/atomicKhalil/bayan/issues
Keywords: pdf,academic,papers,research,extraction,parsing
Classifier: Development Status :: 3 - Alpha
Classifier: Intended Audience :: Developers
Classifier: Intended Audience :: Science/Research
Classifier: Topic :: Scientific/Engineering
Classifier: Topic :: Text Processing
Classifier: License :: OSI Approved :: MIT License
Classifier: Programming Language :: Python :: 3
Classifier: Programming Language :: Python :: 3.8
Classifier: Programming Language :: Python :: 3.9
Classifier: Programming Language :: Python :: 3.10
Classifier: Programming Language :: Python :: 3.11
Classifier: Programming Language :: Python :: 3.12
Requires-Python: >=3.8
License-File: LICENSE
Requires-Dist: PyMuPDF>=1.23.0
Requires-Dist: pdfminer.six>=20221105
Provides-Extra: dataframe
Requires-Dist: pandas>=1.5.0; extra == "dataframe"
Requires-Dist: matplotlib>=3.5.0; extra == "dataframe"
Requires-Dist: Pillow>=9.0.0; extra == "dataframe"
Provides-Extra: llm
Requires-Dist: openai>=1.0.0; extra == "llm"
Requires-Dist: anthropic>=0.7.0; extra == "llm"
Provides-Extra: ml
Requires-Dist: transformers>=4.30.0; extra == "ml"
Requires-Dist: torch>=2.0.0; extra == "ml"
Provides-Extra: dev
Requires-Dist: pytest>=7.0.0; extra == "dev"
Requires-Dist: black>=23.0.0; extra == "dev"
Requires-Dist: flake8>=6.0.0; extra == "dev"
Requires-Dist: mypy>=1.0.0; extra == "dev"
Provides-Extra: all
Requires-Dist: bayan[dataframe,llm,ml]; extra == "all"
Dynamic: author
Dynamic: home-page
Dynamic: license-file
Dynamic: requires-python
